sqlitefspath/__init__.py
sqlitefspath/sqlitefspath.py
sqlitefspath-0.0.1a2.dist-info/licenses/LICENSE
sqlitefspath-0.0.1a2.dist-info/WHEEL
sqlitefspath-0.0.1a2.dist-info/METADATA
sqlitefspath-0.0.1a2.dist-info/RECORD
